auto_ml_models/__init__.py
auto_ml_models/classification.py
auto_ml_models/regression.py
auto_ml_models-0.1.0.dist-info/METADATA
auto_ml_models-0.1.0.dist-info/WHEEL
auto_ml_models-0.1.0.dist-info/top_level.txt
auto_ml_models-0.1.0.dist-info/RECORD
