Metadata-Version: 2.1
Name: auto_ml_models
Version: 0.1.0
Summary: A package to find best machine learning model
Author: Alireza Kiaeipour
Author-email: a.kiaipoor@gmail.com
Requires-Dist: scikit-learn ==1.5.0
Requires-Dist: xgboost ==2.0.3
Requires-Dist: catboost ==1.2.5
